streamlit_event_hook-0.3.3.dist-info/METADATA
streamlit_event_hook-0.3.3.dist-info/WHEEL
streamlit_event_hook-0.3.3.dist-info/license_files/LICENSE
streamlit_event_hook.libs/libgcc_s-b5472b99.so.1
streamlit_event_hook/__init__.py
streamlit_event_hook/streamlit_event_hook.cpython-39-i386-linux-gnu.so
streamlit_event_hook-0.3.3.dist-info/RECORD
