Metadata-Version: 2.3
Name: streamlit-event-hook
Version: 0.3.3
Classifier: Programming Language :: Rust
Classifier: Programming Language :: Python :: Implementation :: CPython
Classifier: Programming Language :: Python :: Implementation :: PyPy
Requires-Dist: patchy >2.6.0
Requires-Dist: streamlit >=1.37
License-File: LICENSE
Summary: A Streamlit component that hooks into page rendering events.
Requires-Python: >=3.8
